{"pageProps":{"initialData":[{"primaryImageSmall":"https://images.metmuseum.org/CRDImages/ep/web-large/DT8844.jpg","title":"Madonna and Child","city":"","artistDisplayBio":"Italian, Florence 1494–1557 Florence","artistDisplayName":"Bachiacca (Francesco d'Ubertino Verdi)","country":"","dimensions":"34 1/4 x 26 1/2 in. (87 x 67.3 cm)","medium":"Oil and gold on wood","objectName":"Painting","objectURL":"https://www.metmuseum.org/art/collection/search/435595","repostory":"Metropolitan Museum of Art, New York, NY","objectID":435595},{"primaryImageSmall":"https://images.metmuseum.org/CRDImages/ep/web-large/DP146473.jpg","title":"Old Woman in an Armchair","city":"","artistDisplayBio":"Dutch, Harlingen 1608–1651 Amsterdam","artistDisplayName":"Jacob Backer","country":"","dimensions":"50 3/8 x 39 1/8 in. (128 x 99.4 cm)","medium":"Oil on canvas","objectName":"Painting","objectURL":"https://www.metmuseum.org/art/collection/search/435596","repostory":"Metropolitan Museum of Art, New York, NY","objectID":435596},{"primaryImageSmall":"https://images.metmuseum.org/CRDImages/ep/web-large/DP121324.jpg","title":"Portrait of an Old Woman","city":"","artistDisplayBio":"Dutch, second quarter 17th century","artistDisplayName":"Jacob Backer","country":"","dimensions":"28 x 24 in. (71.1 x 61 cm)","medium":"Oil on wood","objectName":"Painting","objectURL":"https://www.metmuseum.org/art/collection/search/435597","repostory":"Metropolitan Museum of Art, New York, NY","objectID":435597},{"primaryImageSmall":"https://images.metmuseum.org/CRDImages/ep/web-large/DP146464.jpg","title":"Portrait of a Man, Possibly a Botanist","city":"","artistDisplayBio":"Dutch, Leiden 1584–1657 Leiden","artistDisplayName":"David Bailly","country":"","dimensions":"33 x 24 1/2 in. (83.8 x 62.2 cm)","medium":"Oil on wood","objectName":"Painting","objectURL":"https://www.metmuseum.org/art/collection/search/435598","repostory":"Metropolitan Museum of Art, New York, NY","objectID":435598},{"primaryImageSmall":"https://images.metmuseum.org/CRDImages/ep/web-large/EP603.jpg","title":"Boatmen of Barcelona","city":"","artistDisplayBio":"Spanish, Barcelona 1862–1943 Barcelona","artistDisplayName":"Dionisio Baixeras y Verdaguer","country":"","dimensions":"59 x 83 in. (149.9 x 210.8 cm)","medium":"Oil on canvas","objectName":"Painting","objectURL":"https://www.metmuseum.org/art/collection/search/435599","repostory":"Metropolitan Museum of Art, New York, NY","objectID":435599},{"primaryImageSmall":"https://images.metmuseum.org/CRDImages/ep/web-large/DP164867.jpg","title":"Saint John on Patmos","city":"","artistDisplayBio":"German, Schwäbisch Gmünd (?) 1484/85–1545 Strasbourg","artistDisplayName":"Hans Baldung (called Hans Baldung Grien)","country":"","dimensions":"Overall 35 1/4 x 30 1/4 in. (89.5 x 76.8 cm); painted surface 34 3/8 x 29 3/4 in. (87.3 x 75.6 cm)","medium":"Oil, gold, and white metal on spruce","objectName":"Painting","objectURL":"https://www.metmuseum.org/art/collection/search/435600","repostory":"Metropolitan Museum of Art, New York, NY","objectID":435600},{"primaryImageSmall":"https://images.metmuseum.org/CRDImages/ep/web-large/ep32.100.94.bw.R.jpg","title":"Madonna and Child","city":"","artistDisplayBio":"Italian, Bolognese, active early 16th century","artistDisplayName":"Ercole Banci","country":"","dimensions":"15 1/4 x 12 3/8 in. (38.7 x 31.4 cm)","medium":"Tempera on wood","objectName":"Painting","objectURL":"https://www.metmuseum.org/art/collection/search/435601","repostory":"Metropolitan Museum of Art, New York, NY","objectID":435601},{"primaryImageSmall":"https://images.metmuseum.org/CRDImages/ep/web-large/DP135400.jpg","title":"Madonna and Child with Saints Philip and Agnes","city":"","artistDisplayBio":"Italian, Lombard, active by 1426–died 1450/51","artistDisplayName":"Donato de' Bardi","country":"","dimensions":"Central panel, overall 23 1/2 x 13 1/8 in. (59.7 x 33.3 cm), painted surface 23 1/8 x 12 3/4 in. (58.7 x 32.4 cm); each wing, overall 23 5/8 x 6 in. (60 x 15.2 cm), painted surface 23 1/4 x 5 1/2 in. (59.1 x 14 cm)","medium":"Tempera on wood, gold ground","objectName":"Painting, triptych","objectURL":"https://www.metmuseum.org/art/collection/search/435602","repostory":"Metropolitan Museum of Art, New York, NY","objectID":435602},{"primaryImageSmall":"https://images.metmuseum.org/CRDImages/ep/web-large/ep81.1.656.R.jpg","title":"A Footman Sleeping","city":"","artistDisplayBio":"French, Paris 1825/26–1883 Paris","artistDisplayName":"Charles Bargue","country":"","dimensions":"13 3/4 x 10 1/4 in. (34.9 x 26 cm)","medium":"Oil on wood","objectName":"Painting","objectURL":"https://www.metmuseum.org/art/collection/search/435603","repostory":"Metropolitan Museum of Art, New York, NY","objectID":435603},{"primaryImageSmall":"https://images.metmuseum.org/CRDImages/ep/web-large/DP-29211-001.jpg","title":"A Bashi-Bazouk","city":"","artistDisplayBio":"French, Paris 1825/26–1883 Paris","artistDisplayName":"Charles Bargue","country":"","dimensions":"18 1/4 x 13 1/8 in. (46.4 x 33.3 cm)","medium":"Oil on canvas","objectName":"Painting","objectURL":"https://www.metmuseum.org/art/collection/search/435604","repostory":"Metropolitan Museum of Art, New York, NY","objectID":435604},{"primaryImageSmall":"https://images.metmuseum.org/CRDImages/ep/web-large/DP-20397-001.jpg","title":"Scenes from the Life of Christ","city":"","artistDisplayBio":"Italian, active in Romagna and the Marches, second quarter 14th century","artistDisplayName":"Giovanni Baronzio","country":"","dimensions":"26 1/4 x 15 in. (66.7 x 38.1 cm)","medium":"Tempera on canvas, transferred from wood, gold ground","objectName":"Painting, right wing of a diptych","objectURL":"https://www.metmuseum.org/art/collection/search/435607","repostory":"Metropolitan Museum of Art, New York, NY","objectID":435607},{"primaryImageSmall":"https://images.metmuseum.org/CRDImages/ep/web-large/37132.jpg","title":"Portrait of a Man","city":"","artistDisplayBio":"ca. 1790","artistDisplayName":"Barrois","country":"","dimensions":"Diameter 2 3/4 in. (67 mm)","medium":"Ivory","objectName":"Painting, miniature","objectURL":"https://www.metmuseum.org/art/collection/search/435608","repostory":"Metropolitan Museum of Art, New York, NY","objectID":435608},{"primaryImageSmall":"https://images.metmuseum.org/CRDImages/ep/web-large/80546.jpg","title":"Portrait of a Man","city":"","artistDisplayBio":"British, active ca. 1784–1827","artistDisplayName":"John Barry","country":"","dimensions":"Oval, 2 1/2 x 2 1/8 in. (64 x 54 mm)","medium":"Ivory","objectName":"Painting, miniature","objectURL":"https://www.metmuseum.org/art/collection/search/435609","repostory":"Metropolitan Museum of Art, New York, NY","objectID":435609},{"primaryImageSmall":"https://images.metmuseum.org/CRDImages/ep/web-large/80544.jpg","title":"Portrait of a Woman","city":"","artistDisplayBio":"British, active ca. 1784–1827","artistDisplayName":"John Barry","country":"","dimensions":"Oval, 2 1/2 x 2 1/8 in. (64 x 54 mm)","medium":"Ivory","objectName":"Painting, miniature","objectURL":"https://www.metmuseum.org/art/collection/search/435610","repostory":"Metropolitan Museum of Art, New York, NY","objectID":435610},{"primaryImageSmall":"https://images.metmuseum.org/CRDImages/ep/web-large/175490.jpg","title":"Portrait of a Man, Said to Be John Durham","city":"","artistDisplayBio":"British, active ca. 1784–1827","artistDisplayName":"John Barry","country":"","dimensions":"Oval, 2 5/8 x 2 1/4 in. (67 x 56 mm)","medium":"Ivory","objectName":"Painting, miniature","objectURL":"https://www.metmuseum.org/art/collection/search/435611","repostory":"Metropolitan Museum of Art, New York, NY","objectID":435611},{"primaryImageSmall":"https://images.metmuseum.org/CRDImages/ep/web-large/DP-17017-001.jpg","title":"Madonna and Child with the Young Saint John the Baptist","city":"","artistDisplayBio":"Italian, Florence 1473–1517 Florence","artistDisplayName":"Fra Bartolomeo (Bartolomeo di Paolo del Fattorino)","country":"","dimensions":"23 x 17 1/4 in. (58.4 x 43.8 cm)","medium":"Oil and gold on wood","objectName":"Painting","objectURL":"https://www.metmuseum.org/art/collection/search/435614","repostory":"Metropolitan Museum of Art, New York, NY","objectID":435614},{"primaryImageSmall":"https://images.metmuseum.org/CRDImages/ep/web-large/DT8842.jpg","title":"Portrait of a Man","city":"","artistDisplayBio":"Italian, Florence 1473–1517 Florence","artistDisplayName":"Fra Bartolomeo (Bartolomeo di Paolo del Fattorino)","country":"","dimensions":"Overall 15 5/8 x 12 1/8 in. (39.7 x 30.8 cm); painted surface 15 1/2 x 11 3/4 in. (39.4 x 29.8 cm)","medium":"Oil on wood","objectName":"Painting","objectURL":"https://www.metmuseum.org/art/collection/search/435615","repostory":"Metropolitan Museum of Art, New York, NY","objectID":435615},{"primaryImageSmall":"https://images.metmuseum.org/CRDImages/ep/web-large/DP-23202-001.jpg","title":"Saint Dominic Resuscitating Napoleone Orsini","city":"","artistDisplayBio":"Italian, Modena, active 1460–79","artistDisplayName":"Bartolomeo degli Erri","country":"","dimensions":"14 x 17 1/2 in. (35.6 x 44.5 cm)","medium":"Tempera on canvas, transferred from wood","objectName":"Painting","objectURL":"https://www.metmuseum.org/art/collection/search/435616","repostory":"Metropolitan Museum of Art, New York, NY","objectID":435616},{"primaryImageSmall":"https://images.metmuseum.org/CRDImages/ep/web-large/EP468.jpg","title":"Saint Thomas Aquinas Aided by Saints Peter and Paul","city":"","artistDisplayBio":"Italian, Modena, active 1460–79","artistDisplayName":"Bartolomeo degli Erri","country":"","dimensions":"17 x 12 in. (43.2 x 30.5 cm)","medium":"Tempera on wood","objectName":"Painting","objectURL":"https://www.metmuseum.org/art/collection/search/435617","repostory":"Metropolitan Museum of Art, New York, NY","objectID":435617}]},"__N_SSG":true}